dgi/__init__.py
dgi/core.py
dgi_serve-0.1.0.dev0.dist-info/licenses/LICENSE
dgi_serve-0.1.0.dev0.dist-info/METADATA
dgi_serve-0.1.0.dev0.dist-info/WHEEL
dgi_serve-0.1.0.dev0.dist-info/top_level.txt
dgi_serve-0.1.0.dev0.dist-info/RECORD
