Metadata-Version: 2.4
Name: dgi-serve
Version: 0.1.0.dev0
Summary: DGI: The Deep-neural-network General Inference service & framework.
Author: Wilhelm Jung
License: MIT
Project-URL: Homepage, https://github.com/deepnova/dgi-serve
Project-URL: Issues, https://github.com/deepnova/dgi-serve/issues
Project-URL: Repository, https://github.com/deepnova/dgi-serve.git
Keywords: dgi,dgi-serve,deep-learning,inference
Classifier: Development Status :: 3 - Alpha
Classifier: Intended Audience :: Developers
Classifier: License :: OSI Approved :: MIT License
Classifier: Programming Language :: Python :: 3
Classifier: Programming Language :: Python :: 3.8
Classifier: Programming Language :: Python :: 3.9
Classifier: Programming Language :: Python :: 3.10
Classifier: Programming Language :: Python :: 3.11
Classifier: Programming Language :: Python :: 3.12
Requires-Python: >=3.8
License-File: LICENSE
Provides-Extra: dev
Requires-Dist: pytest>=6.0; extra == "dev"
Requires-Dist: pytest-cov; extra == "dev"
Requires-Dist: black; extra == "dev"
Requires-Dist: flake8; extra == "dev"
Requires-Dist: mypy; extra == "dev"
Dynamic: license-file
